fastmcp_odoo_accounting/__init__.py
fastmcp_odoo_accounting/auth.py
fastmcp_odoo_accounting/config.py
fastmcp_odoo_accounting/logging_setup.py
fastmcp_odoo_accounting/models.py
fastmcp_odoo_accounting/odoo_connector.py
fastmcp_odoo_accounting/server.py
fastmcp_odoo_accounting/prompts/__init__.py
fastmcp_odoo_accounting/prompts/accounting_prompts.py
fastmcp_odoo_accounting/resources/__init__.py
fastmcp_odoo_accounting/resources/accounting_resources.py
fastmcp_odoo_accounting/tools/__init__.py
fastmcp_odoo_accounting/tools/accounts.py
fastmcp_odoo_accounting/tools/invoices.py
fastmcp_odoo_accounting/tools/journals.py
fastmcp_odoo_accounting/tools/partners.py
fastmcp_odoo_accounting/tools/payments.py
fastmcp_odoo_accounting/tools/reports.py
fastmcp_odoo_accounting-1.0.0.dist-info/licenses/LICENSE
fastmcp_odoo_accounting-1.0.0.dist-info/METADATA
fastmcp_odoo_accounting-1.0.0.dist-info/WHEEL
fastmcp_odoo_accounting-1.0.0.dist-info/entry_points.txt
fastmcp_odoo_accounting-1.0.0.dist-info/top_level.txt
fastmcp_odoo_accounting-1.0.0.dist-info/RECORD
