Metadata-Version: 2.4
Name: fastmcp-odoo-accounting
Version: 1.0.0
Summary: A FastMCP server providing read-only access to Odoo 18.3+e Accounting data
Author-email: Markov Kernel <hello@markov.run>
License: MIT
Project-URL: Homepage, https://github.com/markov-kernel/Odoo-mcp
Project-URL: Repository, https://github.com/markov-kernel/Odoo-mcp
Project-URL: Issues, https://github.com/markov-kernel/Odoo-mcp/issues
Classifier: Development Status :: 4 - Beta
Classifier: Intended Audience :: Developers
Classifier: Programming Language :: Python :: 3
Classifier: Programming Language :: Python :: 3.8
Classifier: Programming Language :: Python :: 3.9
Classifier: Programming Language :: Python :: 3.10
Classifier: Programming Language :: Python :: 3.11
Classifier: Programming Language :: Python :: 3.12
Classifier: Topic :: Software Development :: Libraries :: Python Modules
Classifier: Topic :: Office/Business :: Financial :: Accounting
Requires-Python: >=3.10
License-File: LICENSE
Requires-Dist: fastmcp>=0.1.0
Requires-Dist: pydantic>=2.0.0
Requires-Dist: python-dotenv>=1.0.0
Requires-Dist: click>=8.0.0
Requires-Dist: uvicorn>=0.20.0
Requires-Dist: colorlog>=6.0.0
Provides-Extra: dev
Requires-Dist: pytest>=7.0.0; extra == "dev"
Requires-Dist: pytest-asyncio>=0.21.0; extra == "dev"
Requires-Dist: mypy>=1.0.0; extra == "dev"
Requires-Dist: black>=23.0.0; extra == "dev"
Requires-Dist: ruff>=0.1.0; extra == "dev"
Requires-Dist: coverage[toml]>=7.0.0; extra == "dev"
Dynamic: license-file
